README.md
setup.py
dj_loopbreaker.egg-info/PKG-INFO
dj_loopbreaker.egg-info/SOURCES.txt
dj_loopbreaker.egg-info/dependency_links.txt
dj_loopbreaker.egg-info/top_level.txt
loopbreaker/__init__.py
loopbreaker/decorators.py
loopbreaker/tests.py