Metadata-Version: 2.1
Name: dj-loopbreaker
Version: 0.0.1
Summary: Break infinite loops in signals
Home-page: https://gitlab.com/SchoolOrchestration/libs/dj-loopbreaker
Author: Christo Crampton
Author-email: tech@appointmentguru.co
License: UNKNOWN
Platform: UNKNOWN
Classifier: Programming Language :: Python :: 3
Classifier: Operating System :: OS Independent
